{
    "\"On the gravitational nature of time\"": "<Center <Small <Abstract <EqRef <Image <FigRef <Admonition <Boxed <Quote <Vspace",
    "ColorProps": "<Hint <ThemeSwitch <ColorChip",
    "Underline": "<Hint <Ul <TypeDoc",
    "Title": "<Title <TypeDoc",
    "Small": "<Small <TypeDoc",
    "Quote": "<Quote <TypeDoc",
    "Lead": "<Lead <TypeDoc",
    "Large": "<Large <TypeDoc",
    "Highlight": "<Hint <Hl <TypeDoc",
    "EqRef": "<EqRef <TypeDoc",
    "VSpace": "<TypeDoc",
    "TabGroup & Tab": "<TypeDoc <TabGroup <Tab",
    "Grid & GridItem": "<Hint <TypeDoc <Grid <GridItem",
    "Center": "<Center <TypeDoc",
    "Card": "<Card <TypeDoc",
    "Admonition": "<Admonition <Small <TypeDoc",
    "WithTooltip": "<Ul <Color <Hl <TypeDoc",
    "Video": "<Video <RemoteExampleLimitation <TypeDoc",
    "ModelView": "<ModelView <TypeDoc",
    "Image": "<Image <TypeDoc",
    "ErrorMargin": "<ErrorMargin <TypeDoc",
    "Abstract": "<Abstract <TypeDoc",
    "ULLD Syntax": "<AnimatedLogo <Admonition <LogoAsText <Hint <Video <Tag <TagBar <Equation <Image <StaticLink",
    "My Work": "<ComingSoon",
    "Introduction to JSX": "<LogoAsText <SomeComponent <Ul <Hint <Admonition <ThatComponent <ToSquareOrNotToSquare <SomeOtherComponent <StaticLink",
    "Getting Started": "<LogoAsText <Admonition <CodeBlock <Hl <Small <StaticLink <Hint <TabGroup <Tab <Ul",
    "Developer Documentation": "<LogoAsText <TypeDoc <Small <Hint <Button <Admonition <Ul <MyComponentNameOrAlias <StaticLink",
    "ULLD Demos": "<ComingSoon",
    "Story of ULLD": "<LogoAsText <Ul <Center <PayPalQR",
    "About Us": "<Title <LogoAsText <Quote",
    "Why I left Work": "<ComingSoon",
    "Plans for Uh Little Less Dum": "<ComingSoon",
    "Predictions and the theory of gravitational time": "<Small <Image <FigRef <Ul"
}